{
  "name": "Porsche 992 Turbo S 2023",
  "brand": "Porsche",
  "description": "The 911 Turbo models feature incredible performance combined with breath taking driving dynamics. Even though the basic engine layout has not changed, every detail has been optimised, honed and refined. For example, larger exhaust turbochargers and piezo injectors are used for the first time. Exhaust manifolds derived from the 911 GT2 RS improve responsiveness and efficiency, thanks to optimised flow ratios.<br><br>Made By Ceky Performance<br>Patreon: https://www.patreon.com/CekyPerformance<br>Discord: https://discord.gg/VmeReZv3ey<br>Version: 1.0<br><br>Features:<br>-Android Auto<br>-Porsche Light Design ( Ambient Light )<br>-Openable Wing ( Extra A )<br>-Openable Frunk ( Extra B )<br>-Exhaust / ESC OFF / Suspension Active Buttons<br>-Multiple Clusters ( Start Up, Normal , Sport )<br>-Openable Doors ( Extra C )<br>-Extra Headlights (Extra D)<br>-Normal Cluster ( TC 1-2/2 )<br>-Sport Cluster ( TC OFF )<br>-Start Key, Buttons, Turn Signal, Flash, PDK Shifter, etc animations<br>-Realistic Liveries &amp; Specs<br>-Full Paintshop available<br>-Full PBR &amp; Rain Ready",
  "tags": [
    "awd"
  ],
  "class": "street",
  "specs": {
    "bhp": "650 Hp",
    "torque": "800 Nm",
    "weight": "1650 kg",
    "topspeed": "330 km/h",
    "acceleration": "2.6s 0-100",
    "pwratio": "2.54 kg/hp"
  },
  "torqueCurve": [
    [
      0.0,
      23.3846153846154
    ],
    [
      144.0,
      81.4454153846154
    ],
    [
      360.0,
      179.474285714286
    ],
    [
      500.0,
      250.021978021978
    ],
    [
      864.0,
      323.929178021978
    ],
    [
      936.0,
      339.652079120879
    ],
    [
      1000.0,
      352.0
    ],
    [
      2000.0,
      448.0
    ],
    [
      2500.0,
      464.0
    ],
    [
      3000.0,
      505.6
    ],
    [
      3500.0,
      537.6
    ],
    [
      4000.0,
      576.0
    ],
    [
      4500.0,
      608.0
    ],
    [
      5000.0,
      656.0
    ],
    [
      5500.0,
      720.0
    ],
    [
      6000.0,
      800.0
    ],
    [
      6250.0,
      784.0
    ],
    [
      6750.0,
      720.0
    ],
    [
      7000.0,
      672.0
    ],
    [
      7200.0,
      646.4
    ]
  ],
  "powerCurve": [
    [
      0.0,
      0.0
    ],
    [
      72.0,
      0.500616881632653
    ],
    [
      144.0,
      1.55577364897959
    ],
    [
      216.0,
      3.26993621457726
    ],
    [
      288.0,
      5.60828260758017
    ],
    [
      360.0,
      8.57081282798834
    ],
    [
      432.0,
      12.3641372361516
    ],
    [
      500.0,
      16.5830903790087
    ],
    [
      576.0,
      20.2827877504373
    ],
    [
      648.0,
      24.0747740921283
    ],
    [
      792.0,
      32.4965053574344
    ],
    [
      864.0,
      37.1262502810496
    ],
    [
      1000.0,
      46.6938775510204
    ],
    [
      1296.0,
      65.4004976326531
    ],
    [
      1656.0,
      91.1592176326531
    ],
    [
      2000.0,
      118.857142857143
    ],
    [
      2500.0,
      153.877551020408
    ],
    [
      3500.0,
      249.6
    ],
    [
      4500.0,
      362.938775510204
    ],
    [
      5000.0,
      435.102040816327
    ],
    [
      5500.0,
      525.30612244898
    ],
    [
      6000.0,
      636.734693877551
    ],
    [
      6250.0,
      650.0
    ],
    [
      6264.0,
      649.966957714286
    ],
    [
      6336.0,
      649.691888326531
    ],
    [
      6408.0,
      649.240774530612
    ],
    [
      6480.0,
      648.613616326531
    ],
    [
      6552.0,
      647.810413714286
    ],
    [
      6624.0,
      646.831166693878
    ],
    [
      6696.0,
      645.675875265306
    ],
    [
      6750.0,
      644.69387755102
    ],
    [
      6912.0,
      631.647336489796
    ],
    [
      7000.0,
      624.0
    ],
    [
      7056.0,
      622.282752
    ],
    [
      7128.0,
      619.918377795918
    ],
    [
      7200.0,
      617.377959183674
    ]
  ],
  "country": "Germany",
  "year": 2023,
  "author": "Ceky Performance",
  "version": "1.0",
  "url": "https://www.patreon.com/CekyPerformance"
}