{
  "name": "Ford Mustang Boss 302",
  "brand": "Ford",
  "year": "1969",
  "author": "Pessio Garage & abbo90",
  "folderName": "pg_mustard",
  "folderPath": "D:\\Steam\\steamapps\\common\\assettocorsa\\content\\cars\\pg_mustard",
  "specs": {
    "convertedPower": "347kW/472hp",
    "isManufacturerData": false,
    "normalizedAcceleration": "4.7s",
    "normalizedTorque": "529 Nm",
    "normalizedTopSpeed": "270+ km/h",
    "bhp": "472 bhp",
    "torque": "529 Nm",
    "weight": "1318 kg",
    "topspeed": "270+ km/h",
    "acceleration": "0 - 100 kph in 4.7 s",
    "pwratio": "2.79 kg/hp"
  },
  "tags": [
    "#+ rwd",
    "#- manual"
  ],
  "data": {
    "tractionType": "RWD",
    "gearsCount": 4,
    "supportsShifter": true,
    "turboCount": 0
  },
  "ratings": {
    "handling": 0.0,
    "physics": 0.0,
    "realism": 0.0,
    "sound": 0.0,
    "visuals": 0.0,
    "funFactor": 0.0,
    "extraFeatures": 0.0
  }
}